event_chain/__init__.py
event_chain/runner.py
event_chain/app/__init__.py
event_chain/app/utils.py
event_chain/app/apis/__init__.py
event_chain/app/apis/mobile.py
event_chain/app/apis/ticket.py
event_chain/app/controllers/__init__.py
event_chain/app/controllers/admin.py
event_chain/app/controllers/did_auth.py
event_chain/app/controllers/event.py
event_chain/app/controllers/mobile.py
event_chain/app/controllers/ticket.py
event_chain/app/forms/__init__.py
event_chain/app/forms/admin.py
event_chain/app/forms/event.py
event_chain/app/models/__init__.py
event_chain/app/models/admin.py
event_chain/app/models/event.py
event_chain/app/models/mobile.py
event_chain/app/models/sql.py
event_chain/app/models/ticket.py
event_chain/app/models/sql/__init__.py
event_chain/app/models/sql/index_db.py
event_chain/app/models/states/__init__.py
event_chain/app/models/states/account.py
event_chain/app/models/states/asset.py
event_chain/app/models/states/event.py
event_chain/app/models/states/forge_states/__init__.py
event_chain/app/models/states/forge_states/asset_factory_state.py
event_chain/app/models/states/forge_states/asset_state.py
event_chain/app/static/favicon.ico
event_chain/app/static/robots.txt
event_chain/app/static/css/app.css
event_chain/app/static/css/custom.css
event_chain/app/static/images/eventchain_bg_1.jpg
event_chain/app/static/images/eventchain_h.png
event_chain/app/static/images/eventchain_h_2.png
event_chain/app/static/images/home_bg.png
event_chain/app/static/images/stamp.jpg
event_chain/app/static/images/used.png
event_chain/app/static/images/event_img/event_1.png
event_chain/app/static/images/event_img/event_2.png
event_chain/app/static/images/event_img/event_3.png
event_chain/app/static/images/event_img/event_4.png
event_chain/app/static/images/event_img/event_5.png
event_chain/app/static/images/event_img/event_6.png
event_chain/app/static/js/app.js
event_chain/app/templates/layout.html
forge_event_chain-0.27.0.dist-info/LICENSE.txt
forge_event_chain-0.27.0.dist-info/METADATA
forge_event_chain-0.27.0.dist-info/RECORD
forge_event_chain-0.27.0.dist-info/WHEEL
forge_event_chain-0.27.0.dist-info/top_level.txt
