Metadata-Version: 2.1
Name: forge-event-chain
Version: 0.27.0
Summary: A small example package
Home-page: https://github.com/ArcBlock/forge-python-sdk
Author: ArcBlock
Author-email: riley@arcblock.io
License: UNKNOWN
Platform: UNKNOWN
Classifier: Programming Language :: Python :: 3
Classifier: License :: OSI Approved :: MIT License
Classifier: Operating System :: OS Independent
Requires-Dist: Flask (==0.12.4)
Requires-Dist: Flask-AppBuilder (==1.10.0)
Requires-Dist: Flask-Babel (==0.11.1)
Requires-Dist: Flask-Caching (==1.4.0)
Requires-Dist: Flask-Compress (==1.4.0)
Requires-Dist: Flask-Login (==0.2.11)
Requires-Dist: Flask-Migrate (==2.2.1)
Requires-Dist: Flask-OpenID (==1.2.5)
Requires-Dist: flask-qrcode
Requires-Dist: Flask-Script (==2.0.6)
Requires-Dist: Flask-Session (==0.3.1)
Requires-Dist: Flask-SQLAlchemy (==2.1)
Requires-Dist: Flask-Testing (==0.7.1)
Requires-Dist: Flask-WTF (==0.14.2)
Requires-Dist: flask-googlemaps
Requires-Dist: forge-python-sdk
Requires-Dist: requests
Requires-Dist: Flask-Markdown
Requires-Dist: click (==6.7)
